src/ansi-print/__init__.py
src/ansi-print/ansi_print.py
lightman_ansi_print-1.0.0.dist-info/METADATA
lightman_ansi_print-1.0.0.dist-info/WHEEL
lightman_ansi_print-1.0.0.dist-info/licenses/LICENSE
lightman_ansi_print-1.0.0.dist-info/RECORD
